{
  "showHeader": {
    "type": "boolean",
    "default": true,
    "description": "Show header bar",
    "group": "Layout"
  },
  "showBackground": {
    "type": "boolean",
    "default": true,
    "description": "Show element background and border",
    "group": "Layout"
  },
  "showLabel": {
    "type": "boolean",
    "default": true,
    "description": "Show title label in header",
    "group": "Layout"
  },
  "showValue": {
    "type": "boolean",
    "default": true,
    "description": "Show primary value rows",
    "group": "Layout"
  },
  "showSecondaryRows": {
    "type": "boolean",
    "default": true,
    "description": "Show secondary detail rows",
    "group": "Layout"
  },
  "showFooter": {
    "type": "boolean",
    "default": true,
    "description": "Show footer controls",
    "group": "Layout"
  },
  "precision": {
    "type": "number",
    "default": 2,
    "min": 0,
    "max": 6,
    "description": "Decimal places for numeric displays",
    "group": "Layout"
  },
  "footerButtonColor": {
    "type": "text",
    "default": "",
    "group": "Footer",
    "format": "color-alpha",
    "x-theme-default": "accentPrimary",
    "description": "Set Target button background color"
  },
  "labelFontFamily": {
    "type": "text",
    "default": "",
    "group": "Label",
    "format": "font-family"
  },
  "labelFontSize": {
    "type": "number",
    "default": 12,
    "group": "Label",
    "format": "font-size",
    "min": 8,
    "max": 48
  },
  "labelFontWeight": {
    "type": "text",
    "default": "500",
    "group": "Label",
    "format": "font-weight"
  },
  "labelFontStyle": {
    "type": "text",
    "default": "normal",
    "group": "Label",
    "format": "font-style"
  },
  "labelColor": {
    "type": "text",
    "default": "",
    "group": "Label",
    "format": "color-alpha",
    "x-theme-default": "textPrimary"
  },
  "backgroundColor": {
    "type": "text",
    "default": "",
    "group": "Background & Border",
    "description": "Override element background color",
    "format": "color-alpha",
    "x-theme-default": "bgSecondary"
  },
  "headerColor": {
    "type": "text",
    "default": "",
    "group": "Background & Border",
    "description": "Override header background color",
    "format": "color-alpha",
    "x-theme-default": "bgTertiary"
  },
  "borderColor": {
    "type": "text",
    "default": "",
    "group": "Background & Border",
    "description": "Override border color",
    "format": "color-alpha",
    "x-theme-default": "borderColor"
  },
  "image": {
    "type": "text",
    "default": "",
    "group": "Background & Border",
    "description": "Use an image as the card background instead of color/border. When set, background, header, and border are replaced by this image.",
    "format": "file-upload",
    "title": "Background Image",
    "x-accept": "image/*,.png,.jpg,.jpeg,.gif,.webp,.svg,.bmp,.ico,.avif",
    "x-picker-title": "Select Background Image"
  },
  "showInput": { "type": "boolean", "default": true, "group": "Input", "description": "Show the Input section" },
  "inputColor": { "type": "text", "default": "", "group": "Input", "format": "color-alpha", "x-theme-default": "accentGreen", "description": "Input value text color" },
  "inputBg": { "type": "text", "default": "", "group": "Input", "format": "color-alpha", "x-theme-default": "bgTertiary", "description": "Input box background color" },
  "inputLabelColor": { "type": "text", "default": "", "group": "Input", "format": "color-alpha", "x-theme-default": "textSecondary", "description": "Input label text color" },
  "inputFont": { "type": "text", "default": "", "group": "Input", "format": "font-family", "description": "Input value font family" },
  "inputSize": { "type": "number", "default": null, "group": "Input", "format": "font-size", "min": 8, "max": 120, "description": "Input value font size in px" },
  "inputWeight": { "type": "text", "default": "", "group": "Input", "format": "font-weight", "description": "Input value font weight" },
  "inputStyle": { "type": "text", "default": "", "group": "Input", "format": "font-style", "description": "Input value font style" },
  "showReading": { "type": "boolean", "default": true, "group": "Reading", "description": "Show the Value/Reading section" },
  "readingColor": { "type": "text", "default": "", "group": "Reading", "format": "color-alpha", "x-theme-default": "accentGreen", "description": "Reading (Value row) text color" },
  "readingBg": { "type": "text", "default": "", "group": "Reading", "format": "color-alpha", "x-theme-default": "bgTertiary", "description": "Reading (Value row) box background" },
  "readingLabelColor": { "type": "text", "default": "", "group": "Reading", "format": "color-alpha", "x-theme-default": "textSecondary", "description": "Reading (Value row) label color" },
  "readingFont": { "type": "text", "default": "", "group": "Reading", "format": "font-family", "description": "Reading (Value row) font family" },
  "readingSize": { "type": "number", "default": null, "group": "Reading", "format": "font-size", "min": 8, "max": 120, "description": "Reading (Value row) font size in px" },
  "readingWeight": { "type": "text", "default": "", "group": "Reading", "format": "font-weight", "description": "Reading (Value row) font weight" },
  "readingStyle": { "type": "text", "default": "", "group": "Reading", "format": "font-style", "description": "Reading (Value row) font style" },
  "showTarget": { "type": "boolean", "default": true, "group": "Target", "description": "Show the Target section" },
  "targetColor": { "type": "text", "default": "", "group": "Target", "format": "color-alpha", "x-theme-default": "accentGreen", "description": "Target value text color" },
  "targetBg": { "type": "text", "default": "", "group": "Target", "format": "color-alpha", "x-theme-default": "bgTertiary", "description": "Target box background color" },
  "targetLabelColor": { "type": "text", "default": "", "group": "Target", "format": "color-alpha", "x-theme-default": "textSecondary", "description": "Target label text color" },
  "targetFont": { "type": "text", "default": "", "group": "Target", "format": "font-family", "description": "Target value font family" },
  "targetSize": { "type": "number", "default": null, "group": "Target", "format": "font-size", "min": 8, "max": 120, "description": "Target value font size in px" },
  "targetWeight": { "type": "text", "default": "", "group": "Target", "format": "font-weight", "description": "Target value font weight" },
  "targetStyle": { "type": "text", "default": "", "group": "Target", "format": "font-style", "description": "Target value font style" },
  "showBand": { "type": "boolean", "default": true, "group": "Band", "description": "Show the Band section" },
  "bandColor": { "type": "text", "default": "", "group": "Band", "format": "color-alpha", "x-theme-default": "accentGreen", "description": "Band value text color" },
  "bandLabelColor": { "type": "text", "default": "", "group": "Band", "format": "color-alpha", "x-theme-default": "textSecondary", "description": "Band label text color" },
  "bandFont": { "type": "text", "default": "", "group": "Band", "format": "font-family", "description": "Band value font family" },
  "bandSize": { "type": "number", "default": null, "group": "Band", "format": "font-size", "min": 8, "max": 120, "description": "Band value font size in px" },
  "bandWeight": { "type": "text", "default": "", "group": "Band", "format": "font-weight", "description": "Band value font weight" },
  "bandStyle": { "type": "text", "default": "", "group": "Band", "format": "font-style", "description": "Band value font style" }
}
